<?xml version="1.0" encoding="UTF-8"?>
<casConsumerDescription xmlns="http://uima.apache.org/resourceSpecifier">
  <frameworkImplementation>org.apache.uima.java</frameworkImplementation>
  <implementationName>edu.pitt.dbmi.xmeso.ctakes.ae.XMIWriter</implementationName>
  <processingResourceMetaData>
    <name>XMESO_XmiWriter_CasConsumerDescriptor</name>
    <description>A convenient wrapper to XMI writer capability</description>
    <version>1.0</version>
    <vendor>University of Pittsburgh Department of Bioinformatics</vendor>
    <configurationParameters searchStrategy="language_fallback">
      <configurationParameter>
        <name>OutputDirectory</name>
        <description>Directory to which XMI files are to be written</description>
        <type>String</type>
        <multiValued>false</multiValued>
        <mandatory>true</mandatory>
      </configurationParameter>
    </configurationParameters>
    <configurationParameterSettings>
      <nameValuePair>
        <name>OutputDirectory</name>
        <value>
          <string>data/output/medkat/upmc</string>
        </value>
      </nameValuePair>
    </configurationParameterSettings>
    <typeSystemDescription>
      <imports>
        <import location="../types/XmesoSystemDescriptor.xml"/>
      </imports>
    </typeSystemDescription>
    <typePriorities/>
    <fsIndexCollection/>
    <capabilities>
      <capability>
        <inputs/>
        <outputs/>
        <languagesSupported/>
      </capability>
    </capabilities>
  <operationalProperties>
      <modifiesCas>false</modifiesCas>
      <multipleDeploymentAllowed>false</multipleDeploymentAllowed>
      <outputsNewCASes>false</outputsNewCASes>
    </operationalProperties>
  </processingResourceMetaData>
  <resourceManagerConfiguration/>
</casConsumerDescription>
